{
    "results": [
        {
            "id": "97eedd8c-bb2d-452a-a9e9-6da571ff2a7b",
            "name": "Article 1",
            "type": "article",
            "children": {
                "id": "52a2318f-f9f5-40b8-bf7e-d95681e56fe4",
                "name": "Verse 1",
                "number": "(1)",
                "type": "verse",
                "content": "\"Bank Rakyat Indonesia\" yang dahulu berturut-turut bernama \"Algemeene Volkscredietbank\" dan \"Syumin Ginko\" adalah Bank Pemerintah.",
                "explanation": "Tidak ada Penjelasan"
            }
        },
        {
            "id": "fd47fec4-d63d-432a-877d-cec65f688506",
            "name": "Article 2",
            "type": "article",
            "children": {
                "id": "9b873966-c3fe-4fdb-82d7-9e5f627429ca",
                "name": "Verse 1",
                "number": "(1)",
                "type": "verse",
                "content": "Daerah pekerjaan Bank Rakyat Indonesia ialah seluruh Indonesia.",
                "explanation": "Tidak ada Penjelasan"
            }
        },
        {
            "id": "1eb2cc5d-a9ea-44f0-aa9e-5cad4b9f0985",
            "name": "Article 3",
            "type": "article",
            "children": {
                "id": "6f6e5a07-f180-465d-9157-74b8d7b42989",
                "name": "Verse 1",
                "number": "(1)",
                "type": "verse",
                "content": "Usaha Bank Rakyat Indonesia adalah:\n1. memberi pinjaman kepada rakyat,\n2. menerima tabungan,\n3. menjalankan pekerjaan Bank pada umunya dan\n4. Usaha-usaha lain yang diserahkan oleh Pemerintah kepadanya. Bank Rakyat Indonesia mempunyai otonomi dalam menyelenggarakan usahanya.",
                "explanation": "Tidak ada Penjelasan"
            }
        },
        {
            "id": "02460882-5117-4cc9-8c71-5c6edb6d1c20",
            "name": "Article 4",
            "type": "article",
            "children": {
                "id": "8970cde2-e2e8-447c-bb1b-305cfa141f18",
                "name": "Verse 1",
                "number": "(1)",
                "type": "verse",
                "content": "Pimpinan Bank Rakyat Indonesia dipegang oleh suatu Dewan Pimpinan yang terdiri dari:\na. seorang Presiden.\nb. sekurang-kurangnya dua orang Direktur yaitu :\nPengganti Presiden pertama dan Direktur Penulis merangkap pengganti Presiden yang kedua, Presiden dan direktur-direkturnya diangkat dan dipecat oleh Menteri Kemakmuran.",
                "explanation": "Tidak ada Penjelasan"
            }
        },
        {
            "id": "4244ebd5-1f07-4fd3-b055-fc279127234b",
            "name": "Article 5",
            "type": "article",
            "children": {
                "id": "5d236869-dc29-4181-8dde-7bcaa0d4791a",
                "name": "Verse 1",
                "number": "(1)",
                "type": "verse",
                "content": "Selama Pemerintah belum mengadakan peraturan-peraturan tersendiri, maka semua\npekerjaan dilakukan menurut peraturan-peraturan yang ada sekarang dan menurut\naturan ini, segala sesuatu jika tidak bertentangan dengan undang-undang Negara.",
                "explanation": "Tidak ada Penjelasan"
            }
        },
        {
            "id": "59f2e591-1d13-4e10-96a0-96ed115b0bdf",
            "name": "Article 6",
            "type": "article",
            "children": {
                "id": "ba3d1217-b586-4a56-8633-6f0927d44884",
                "name": "Verse 1",
                "number": "(1)",
                "type": "verse",
                "content": "Aturan ini dinamakan \"Aturan Bank Rakyat Indonesia\" dan mulai berlaku pada hari\ndiumumkan.",
                "explanation": "Tidak ada Penjelasan"
            }
        }
    ],
    "metadata": {
        "Nomor": "1",
        "Tahun": "1946",
        "Tentang": "Not Available",
        "Menimbang": {
            "Introduction": "\nNot Available"
        },
        "Mengingat": {
            "Introduction": "\nNot Available"
        },
        "Menetapkan": "\n\"Aturan Bank Rakyat Indonesia\" sebagai berikut",
        "tanggal sah": ""
    }
}