{
    "results": [
        {
            "id": "11d5a331-12ee-4e0b-b9f4-5731ad7dedc3",
            "name": "Chapter I",
            "title": "\nPENGALIHAN BENTUK DAN PEMBUBARAN",
            "type": "chapter",
            "children": [
                {
                    "id": "fec00f60-091f-4d91-815a-6a07588eff28",
                    "name": "Article 1",
                    "type": "article",
                    "children": [
                        {
                            "id": "fdf5caf9-71cf-4b98-9607-770e4fe20937",
                            "name": "Verse 1",
                            "number": "1",
                            "type": "verse",
                            "content": " Perusahaan Umum (PERUM) Asuransi Sosial Tenaga Kerja yang\ndidirikan dengan Peraturan Pemerintah Nomor 34 Tahun 1977\ndialihkan bentuknya menjadi Perusahaan Perseroan (PERSERO)\nsebagaimana dimaksud dalam Undang-undang Nomor 9 Tahun\n1969.",
                            "explanation": "Tidak ada Penjelasan"
                        },
                        {
                            "id": "15b07edb-9387-4fbd-b079-abbb536e0eb9",
                            "name": "Verse 2",
                            "number": "2",
                            "type": "verse",
                            "content": " Dengan dialihkannya bentuk Perusahaan Umum (PERUM) Asuransi\nSosial Tenaga Kerja menjadi Perusahaan Perseroan (PERSERO)\nsebagaimana dimaksud dalam ayat (1), Perusahaan Umum\n(PERUM) Asuransi Sosial Tenaga Kerja dinyatakan bubar pada saat\npendirian Perusahaan Perseroan (PERSERO) tersebut dengan\nketentuan bahwa segala hak dan kewajiban, kekayaan serta\npegawai dari Perusahaan Umum (PERUM) Asuransi Sosial Tenaga\nKerja yang ada pada saat pembubarannya beralih kepada\nPERSERO yang bersangkutan.",
                            "explanation": "Tidak ada Penjelasan"
                        }
                    ]
                }
            ]
        },
        {
            "id": "8d520bc0-a9c9-4bd7-843f-e02b2fef4a49",
            "name": "Chapter II",
            "title": "\nMAKSUD DAN TUJUAN",
            "type": "chapter",
            "children": [
                {
                    "id": "5064e9f8-cfe0-47ee-abf0-34c3f4e6f353",
                    "name": "Article 2",
                    "type": "article",
                    "children": {
                        "id": "bddbefc3-412b-4118-8f40-e2c47e694f5a",
                        "name": "Verse 1",
                        "number": "(1)",
                        "type": "verse",
                        "content": "\nMaksud dan tujuan Perusahaan Perseroan (PERSERO) sebagaimana\ndimaksud dalam Pasal 1 adalah untuk menyelenggarakan :\n1. Usaha Asuransi Sosial Tenaga Kerja yang meliputi:\n   a. Asuransi kecelakaan kerja;\n   b. Asuransi hari tua;\n   c. Asuransi kematian.\n2. Usaha-usaha lain dalam rangka perlindungan dan kesejahteraan\n   tenaga kerja dengan persetujuan Menteri Tenaga Kerja.",
                        "explanation": "Tidak ada Penjelasan"
                    }
                }
            ]
        },
        {
            "id": "188d0371-47a4-4fab-a18e-2d08bf376ae1",
            "name": "Chapter III",
            "title": "\nMODAL PERSERO",
            "type": "chapter",
            "children": [
                {
                    "id": "44be4565-d291-4e4b-bd6f-8737891ece01",
                    "name": "Article 3",
                    "type": "article",
                    "children": [
                        {
                            "id": "69e2c38a-db52-4667-8344-b49d0c8d336d",
                            "name": "Verse 1",
                            "number": "1",
                            "type": "verse",
                            "content": " Modal Perusahaan Perseroan (PERSERO) yang ditempatkan dan\n    disetor pada saat pendiriannya berasal dari kekayaan Negara\n    yang tertanam dalam Perusahaan Umum (PERUM) Asuransi Sosial\n(2) Nilai kekayaan Negara sebagaimana dimaksud dalam ayat (1)\nditetapkan oleh Menteri Keuangan berdasarkan hasil perhitungan\nbersama oleh Departemen Keuangan dan Departemen Tenaga\nKerja.",
                            "explanation": "Tidak ada Penjelasan"
                        },
                        {
                            "id": "6d679047-7cda-4b9f-8d52-66f767421ed6",
                            "name": "Verse 3",
                            "number": "3",
                            "type": "verse",
                            "content": " Ketentuan-ketentuan lain mengenai permodalan Perusahaan\nPerseroan (PERSERO) diatur dalam Anggaran Dasarnya. termasuk\nketentuan mengenai modal dasar PERSERO yang terbagi atas\nsaham-saham sesuai dengan ketentuan Peraturan Pemerintah\nNomor 12 Tahun 1969 sebagaimana telah diubah dengan\nPeraturan Pemerintah Nomor 14 Tahun 1972.",
                            "explanation": "Tidak ada Penjelasan"
                        },
                        {
                            "id": "7ab0fcff-388a-4e18-8752-514f1efba8db",
                            "name": "Verse 4",
                            "number": "4",
                            "type": "verse",
                            "content": " Neraca Pembukaan Perusahaan Perseroan (PERSERO) ditetapkan\noleh Menteri Keuangan.",
                            "explanation": "Tidak ada Penjelasan"
                        }
                    ]
                }
            ]
        },
        {
            "id": "7fd55576-b97a-4b3d-9ab2-9036d22961de",
            "name": "Chapter IV",
            "title": "\nPELAKSANAAN PENDIRIAN PERSERO",
            "type": "chapter",
            "children": [
                {
                    "id": "5ad2b8ef-f1cd-4cfd-8cfb-64380a9b2305",
                    "name": "Article 4",
                    "type": "article",
                    "children": {
                        "id": "f70e0e69-8f04-49a9-bae9-3b905d866166",
                        "name": "Verse 1",
                        "number": "(1)",
                        "type": "verse",
                        "content": "\nPelaksanaan pendirian Perusahaan Perseroan (PERSERO) sebagaimana\ndimaksud dalam Pasal 1 dilakukan menurut ketentuan Kitab\nUndang-undang Hukum Dagang (Staatsblad Tahun 1847 Nomor 23)\nsebagaimana telah beberapa kali diubah, terakhir dengan\nUndang-undang Nomor 4 Tahun 1971 dengan memperhatikan\nketentuan-ketentuan yang tercantum dalam Peraturan Pemerintah\nNomor 12 Tahun 1969 sebagaimana telah diubah dengan Peraturan\nPemerintah Nomor 24 Tahun 1972.",
                        "explanation": "Tidak ada Penjelasan"
                    }
                },
                {
                    "id": "b42f9a2c-59b7-440d-8332-167904dd37a9",
                    "name": "Article 5",
                    "type": "article",
                    "children": [
                        {
                            "id": "556eeb90-6dac-4386-9a9f-96a9ecad5f7a",
                            "name": "Verse 1",
                            "number": "1",
                            "type": "verse",
                            "content": " Penyelesaian pendirian Perusahaan Perseroan (PERSERO)\nsebagaimana dimaksud dalam Pasal 4 dikuasakan kepada Menteri\nKeuangan.",
                            "explanation": "Tidak ada Penjelasan"
                        },
                        {
                            "id": "d6ea9b08-1e04-417a-b8f1-633bfe71d862",
                            "name": "Verse 2",
                            "number": "2",
                            "type": "verse",
                            "content": " Menteri Keuangan dapat menyerahkan kekuasaan sebagaimana\ndimaksud dalam ayat (1) dengan disertai hak substitusi kepada\nMenteri Tenaga Kerja dengan ketentuan bahwa Rancangan\nAnggaran Dasar Perusahaan Perseroan (PERSERO) harus mendapat\npersetujuan terlebih dahulu dari Menteri Keuangan.",
                            "explanation": "Tidak ada Penjelasan"
                        }
                    ]
                }
            ]
        },
        {
            "id": "bcaf8348-a27e-46fc-8d0e-1b6d56300675",
            "name": "Chapter V",
            "title": "\nKETENTUAN PENUTUP",
            "type": "chapter",
            "children": [
                {
                    "id": "e30ce417-2645-4256-8acb-cf43f57685b8",
                    "name": "Article 6",
                    "type": "article",
                    "children": {
                        "id": "192bba65-5105-4c04-b794-bd3042e8e04c",
                        "name": "Verse 1",
                        "number": "(1)",
                        "type": "verse",
                        "content": "\nTerhitung sejak berdirinya Perusahaan Perseroan (PERSERO) dan\ndibubarkannya Perusahaan Umum (PERUM) Asuransi Sosial Tenaga\nKerja, Peraturan Pemerintah Nomor 34 Tahun 1977 dinyatakan tidak\nberlaku.",
                        "explanation": "Tidak ada Penjelasan"
                    }
                },
                {
                    "id": "c3ed563c-9c44-4ce2-9258-a9aba0b812f0",
                    "name": "Article 7",
                    "type": "article",
                    "children": {
                        "id": "7d28f729-c6e2-48f8-9a45-dc04a84560b8",
                        "name": "Verse 1",
                        "number": "(1)",
                        "type": "verse",
                        "content": "\nKetentuan lebih lanjut yang diperlukan bagi pelaksanaan Peraturan\nPemerintah ini diatur oleh Menteri Keuangan dan Menteri Tenaga\nKerja baik secara bersama maupun sendiri-sendiri sesuai dengan\nbidang tugasnya masing masing.",
                        "explanation": "Tidak ada Penjelasan"
                    }
                },
                {
                    "id": "c4d7c173-b76a-450b-ba21-02f41f2b9a82",
                    "name": "Article 8",
                    "type": "article",
                    "children": {
                        "id": "a98f32c1-4dcb-444e-b46a-a1a5c1aee9b6",
                        "name": "Verse 1",
                        "number": "(1)",
                        "type": "verse",
                        "content": "\nPeraturan Pemerintah ini mulai berlaku pada tanggal diundangkan.\nAgar setiap orang mengetahuinya, memerintahkan pengundangan\nPeraturan Pemerintah ini dengan penempatannya dalam Lembaran\nNegara Republik Indonesia.",
                        "explanation": "Tidak ada Penjelasan"
                    }
                }
            ]
        }
    ],
    "metadata": {
        "Nomor": "19",
        "Tahun": "1990",
        "Tentang": "PENGALIHAN BENTUK PERUSAHAAN UMUM (PERUM) ASURANSI SOSIAL TENAGA KERJA\nMENJADI PERUSAHAAN PERSEROAN (PERSERO)",
        "Menimbang": {
            "Introduction": "",
            "a": " bahwa dalam rangka upaya meningkatkan efisiensi dan efektifitas\nusaha, maka Perusahaan Umum (PERUM) Asuransi Sosial Tenaga\nKerja yang didirikan dengan Peraturan Pemerintah Nomor 34 Tahun\n1977 dinilai memenuhi persyaratan untuk dialihkan bentuknya\nmenjadi Perusahaan Perseroan (PERSERO);",
            "b": " bahwa sehubungan dengan hal tersebut di atas, pengalihan bentuk\nPerusahaan Umum (PERUM) Asuransi Sosial Tenaga Kerja menjadi\nPerusahaan Perseroan (PERSERO), perlu ditetapkan dengan\nPeraturan Pemerintah;"
        },
        "Mengingat": {
            "Introduction": "",
            "1": " Pasal 5 ayat (2) Undang-Undang Dasar 1945;",
            "2": " Kitab Undang-undang Hukum Dagang (Staatsblad Tahun 1847 Nomor\n23) sebagaimana telah beberapa kali diubah, terakhir dengan\nUndang-undang Nomor 4 Tahun 1971 (Lembaran Negara Tahun 1971\nNomor 20, Tambahan Lembaran Negara Nomor 2959);",
            "3": " Undang-undang Nomor 9 Tahun 1969 tentang Penetapan Peraturan\nPemerintah Pengganti Undang-undang Nomor 1 Tahun 1969 tentang\nBentuk-bentuk Usaha Negara (Lembaran Negara Tahun 1969 Nomor\n16, Tambahan Lembaran Negara Nomor 2890) menjadi\nUndang-undang (Lembaran Negara Tahun 1969 Nomor 40, Tambahan\nLembaran Negara Nomor 2904);",
            "4": " Peraturan Pemerintah Nomor 12 Tahun 1969 tentang Perusahaan\nPerseroan (PERSERO) (Lembaran Negara Tahun 1969 Nomor 21,\nTambahan Lembaran Negara Nomor 2894) sebagaimana telah\ndiubah dengan Peraturan Pemerintah Nomor 24 Tahun 1972"
        },
        "Menetapkan": "\nPERATURAN PEMERINTAH REPUBLIK INDONESIA TENTANG PENGALIHAN\nBENTUK PERUSAHAAN UMUM (PERUM) ASURANSI SOSIAL TENAGA KERJA\nMENJADI PERUSAHAAN PERSEROAN (PERSERO).",
        "tanggal sah": "30 Mei 1990"
    }
}